<?xml version="1.0" encoding="utf-8"?>
<!DOCTYPE hibernate-mapping PUBLIC "-//Hibernate/Hibernate Mapping DTD 3.0//EN"
                                   "http://hibernate.sourceforge.net/hibernate-mapping-3.0.dtd">
<!-- 
    Mapping file autogenerated by MyEclipse Persistence Tools
-->
<hibernate-mapping>
 <class name="entity.Car" schema="HIBERNATE" table="CAR">
  <id name="cid" type="int">
   <column name="CID"/>
   <generator class="assigned"/>
  </id>
  <property name="name" type="java.lang.String">
   <column length="50" name="NAME" />
  </property>
  <property name="brand" type="java.lang.String">
   <column length="50" name="BRAND"/>
  </property>
  <one-to-one name="license" class="entity.License" cascade="all" lazy="false"/>

 </class>
</hibernate-mapping>
